{
  "base": "https://loyad.vercel.app",
  "at": "2026-06-16T09:32:11.044Z",
  "pass": 23,
  "skip": 4,
  "fail": 0,
  "results": [
    {
      "feature": "auth",
      "name": "demo login",
      "status": "PASS",
      "detail": "세션 확보"
    },
    {
      "feature": "catalog",
      "name": "GET /api/extensions",
      "status": "PASS",
      "detail": "catalog 8개"
    },
    {
      "feature": "catalog",
      "name": "studio /law_mcp",
      "status": "PASS",
      "detail": "HTTP 200"
    },
    {
      "feature": "catalog",
      "name": "studio /dart_reports",
      "status": "PASS",
      "detail": "HTTP 200"
    },
    {
      "feature": "catalog",
      "name": "studio /voice_studio",
      "status": "PASS",
      "detail": "HTTP 200"
    },
    {
      "feature": "catalog",
      "name": "studio /marketing_harness",
      "status": "PASS",
      "detail": "HTTP 200"
    },
    {
      "feature": "catalog",
      "name": "studio /ai_image_gen",
      "status": "PASS",
      "detail": "HTTP 200"
    },
    {
      "feature": "law_mcp",
      "name": "POST 비인증 401",
      "status": "PASS",
      "detail": "로그인 필요"
    },
    {
      "feature": "law_mcp",
      "name": "GET tools",
      "status": "PASS",
      "detail": "5 tools"
    },
    {
      "feature": "law_mcp",
      "name": "search_law",
      "status": "PASS",
      "detail": "items 0"
    },
    {
      "feature": "law_mcp",
      "name": "get_law_article",
      "status": "PASS",
      "detail": "source=fallback"
    },
    {
      "feature": "law_mcp",
      "name": "search_precedents",
      "status": "PASS",
      "detail": "count=0"
    },
    {
      "feature": "law_mcp",
      "name": "external_links",
      "status": "PASS",
      "detail": "URL 생성"
    },
    {
      "feature": "dart_reports",
      "name": "GET corp index",
      "status": "PASS",
      "detail": "configured=false, corps=10"
    },
    {
      "feature": "dart_reports",
      "name": "corp_search",
      "status": "PASS",
      "detail": "hits=1"
    },
    {
      "feature": "dart_reports",
      "name": "disclosures",
      "status": "SKIP",
      "detail": "OPENDART_API_KEY 미설정"
    },
    {
      "feature": "dart_reports",
      "name": "financial",
      "status": "SKIP",
      "detail": "OPENDART_API_KEY 미설정"
    },
    {
      "feature": "voice_studio",
      "name": "POST 비인증 401",
      "status": "PASS",
      "detail": "로그인 필요"
    },
    {
      "feature": "voice_studio",
      "name": "빈 텍스트 400",
      "status": "PASS",
      "detail": "검증 OK"
    },
    {
      "feature": "voice_studio",
      "name": "대본 생성",
      "status": "SKIP",
      "detail": "Gemini 미설정"
    },
    {
      "feature": "marketing_harness",
      "name": "POST 비인증 401",
      "status": "PASS",
      "detail": "로그인 필요"
    },
    {
      "feature": "marketing_harness",
      "name": "빈 주제 400",
      "status": "PASS",
      "detail": "검증 OK"
    },
    {
      "feature": "marketing_harness",
      "name": "harness blog",
      "status": "SKIP",
      "detail": "Gemini 미설정"
    },
    {
      "feature": "ai_image_gen",
      "name": "POST 비인증 401",
      "status": "PASS",
      "detail": "로그인 필요"
    },
    {
      "feature": "ai_image_gen",
      "name": "빈 prompt",
      "status": "PASS",
      "detail": "HTTP 400"
    },
    {
      "feature": "image_process",
      "name": "POST 비인증 401",
      "status": "PASS",
      "detail": "로그인 필요"
    },
    {
      "feature": "image_process",
      "name": "optimize PNG",
      "status": "PASS",
      "detail": "out=96b"
    }
  ]
}